{
				  "version": "4.5.1",
				  "objects": [
					{
					  "type": "image",
					  "version": "4.5.1",
					  "originX": "left",
					  "originY": "top",
					  "left": 1620,
					  "top": 86,
					  "width": 354,
					  "height": 827,
					  "fill": "rgb(0,0,0)",
					  "stroke": null,
					  "strokeWidth": 0,
					  "strokeDashArray": null,
					  "strokeLineCap": "butt",
					  "strokeDashOffset": 0,
					  "strokeLineJoin": "miter",
					  "strokeUniform": false,
					  "strokeMiterLimit": 4,
					  "scaleX": 1,
					  "scaleY": 1,
					  "angle": 0,
					  "flipX": false,
					  "flipY": false,
					  "opacity": 1,
					  "shadow": null,
					  "visible": true,
					  "backgroundColor": "",
					  "fillRule": "nonzero",
					  "paintFirst": "fill",
					  "globalCompositeOperation": "source-over",
					  "skewX": 0,
					  "skewY": 0,
					  "cropX": 0,
					  "cropY": 0,
					  "src": "",
					  "name": "qrCode",					  
					  "crossOrigin": null,
					  "filters": []
					},
					{
					  "type": "i-text",
					  "version": "4.5.1",
					  "originX": "left",
					  "originY": "top",
					  "left": 1426.66,
					  "top": 907.33,
					  "width": 149.25,
					  "height": 33.9,
					  "fill": "black",
					  "stroke": null,
					  "strokeWidth": 1,
					  "strokeDashArray": null,
					  "strokeLineCap": "butt",
					  "strokeDashOffset": 0,
					  "strokeLineJoin": "miter",
					  "strokeUniform": false,
					  "strokeMiterLimit": 4,
					  "scaleX": 1,
					  "scaleY": 1,
					  "angle": 0,
					  "flipX": false,
					  "flipY": false,
					  "opacity": 1,
					  "shadow": null,
					  "visible": true,
					  "backgroundColor": "",
					  "fillRule": "nonzero",
					  "paintFirst": "fill",
					  "globalCompositeOperation": "source-over",
					  "skewX": 0,
					  "skewY": 0,
					  "text": "33cl - 5%",
					  "fontSize": 30,
					  "fontWeight": "normal",
					  "fontFamily": "Arial Black",
					  "fontStyle": "normal",
					  "lineHeight": 1.16,
					  "underline": false,
					  "overline": false,
					  "linethrough": false,
					  "textAlign": "left",
					  "textBackgroundColor": "",
					  "charSpacing": 0,
					  "path": null,
					  "direction": "ltr",
					  "styles": {}
					},
					{
					  "type": "i-text",
					  "version": "4.5.1",
					  "originX": "left",
					  "originY": "top",
					  "left": 26.67,
					  "top": 748.8,
					  "width": 1547.01,
					  "height": 191.2,
					  "fill": "black",
					  "stroke": null,
					  "strokeWidth": 1,
					  "strokeDashArray": null,
					  "strokeLineCap": "butt",
					  "strokeDashOffset": 0,
					  "strokeLineJoin": "miter",
					  "strokeUniform": false,
					  "strokeMiterLimit": 4,
					  "scaleX": 1,
					  "scaleY": 1,
					  "angle": 0,
					  "flipX": false,
					  "flipY": false,
					  "opacity": 1,
					  "shadow": null,
					  "visible": true,
					  "backgroundColor": "",
					  "fillRule": "nonzero",
					  "paintFirst": "fill",
					  "globalCompositeOperation": "source-over",
					  "skewX": 0,
					  "skewY": 0,
					  "text": "Blågula Bilen köper lastbilar / 4x4-pickups för donerade pengar, fyller dem med förnödenheter \noch donerar dem till Ukraina. Brygg för Ukraina består av hembryggare och mikrobryggerier \nsom skänker delar av sin produktion till förmån för Ukraina. \nHjälp oss hjälpa Ukraina genom att swisha (minst) 100:- till Blågula Bilen. \nSom tack bjuder vi dig på en ÖL! Tack för ditt stöd!",
					  "fontSize": 30,
					  "fontWeight": "bold",
					  "fontFamily": "Arial Black",
					  "fontStyle": "normal",
					  "lineHeight": 1.16,
					  "underline": false,
					  "overline": false,
					  "linethrough": false,
					  "textAlign": "left",
					  "textBackgroundColor": "",
					  "charSpacing": 0,
					  "path": null,
					  "direction": "ltr",
					  "styles": {}
					}
				  ],
				  "backgroundImage": {
					"type": "image",
					"version": "4.5.1",
					"originX": "left",
					"originY": "top",
					"left": 0,
					"top": 0,
					"width": 2000,
					"height": 1000,
					"fill": "rgb(0,0,0)",
					"stroke": null,
					"strokeWidth": 0,
					"strokeDashArray": null,
					"strokeLineCap": "butt",
					"strokeDashOffset": 0,
					"strokeLineJoin": "miter",
					"strokeUniform": false,
					"strokeMiterLimit": 4,
					"scaleX": 1,
					"scaleY": 1,
					"angle": 0,
					"flipX": false,
					"flipY": false,
					"opacity": 1,
					"shadow": null,
					"visible": true,
					"backgroundColor": "",
					"fillRule": "nonzero",
					"paintFirst": "fill",
					"globalCompositeOperation": "source-over",
					"skewX": 0,
					"skewY": 0,
					"cropX": 0,
					"cropY": 0,
					"src": "",
					"crossOrigin": null,
					"filters": []
				  }
				}